MANIFEST.in
README.md
requirements.txt
setup.cfg
setup.py
versioneer.py
pvsim/__init__.py
pvsim/__main__.py
pvsim/_version.py
pvsim/launcher.py
pvsim.egg-info/PKG-INFO
pvsim.egg-info/SOURCES.txt
pvsim.egg-info/dependency_links.txt
pvsim.egg-info/entry_points.txt
pvsim.egg-info/requires.txt
pvsim.egg-info/top_level.txt