Metadata-Version: 2.1
Name: pvsim
Version: 0.1.1
Summary: Simulator of PVAccess PVs
Home-page: UNKNOWN
Author: hhslepicka
License: Apache License 2.0
Platform: UNKNOWN
